skywatchai/SkywatchAI.py
skywatchai/SkywatchDB.py
skywatchai/__init__.py
skywatchai/utils.py
skywatchai/model/FaceNet.py
skywatchai/model/__init__.py
skywatchai-0.0.3.dist-info/METADATA
skywatchai-0.0.3.dist-info/WHEEL
skywatchai-0.0.3.dist-info/top_level.txt
skywatchai-0.0.3.dist-info/RECORD
